ezpycolor.py
ezpycolor-0.1.0.dist-info/LICENSE
ezpycolor-0.1.0.dist-info/METADATA
ezpycolor-0.1.0.dist-info/WHEEL
ezpycolor-0.1.0.dist-info/top_level.txt
ezpycolor-0.1.0.dist-info/RECORD
