Metadata-Version: 2.1
Name: ezpycolor
Version: 0.1.0
Summary: simple colorization of strings in Python
Home-page: https://github.com/bonifield/ezpycolor
Author: James Bonifield
Author-email: bonifield.tools@gmail.com
License: UNKNOWN
Platform: UNKNOWN
Classifier: Programming Language :: Python :: 3
Classifier: License :: OSI Approved :: MIT License
Classifier: Operating System :: OS Independent
License-File: LICENSE
